LICENSE
MANIFEST.in
README.md
README.rst
requirements.txt
setup.py
django_driver27.egg-info/PKG-INFO
django_driver27.egg-info/SOURCES.txt
django_driver27.egg-info/dependency_links.txt
django_driver27.egg-info/requires.txt
django_driver27.egg-info/top_level.txt
dr27demo/__init__.py
dr27demo/manage.py
dr27demo/dr27app/__init__.py
dr27demo/dr27app/base_settings.py
dr27demo/dr27app/local_settings.py
dr27demo/dr27app/pytest_settings.py
dr27demo/dr27app/settings.py
dr27demo/dr27app/test_settings.py
dr27demo/dr27app/urls.py
dr27demo/dr27app/views.py
dr27demo/dr27app/wsgi.py
driver27/__init__.py
driver27/apps.py
driver27/common.py
driver27/config.py
driver27/decorators.py
driver27/models.py
driver27/points_calculator.py
driver27/punctuation.py
driver27/rank.py
driver27/records.py
driver27/stats.py
driver27/streak.py
driver27/teammates.py
driver27/views.py
driver27/views_ajax.py
driver27/admin/__init__.py
driver27/admin/admin.py
driver27/admin/common.py
driver27/admin/filters.py
driver27/admin/forms.py
driver27/admin/formsets.py
driver27/admin/inlines.py
driver27/api/__init__.py
driver27/api/common.py
driver27/api/routes.py
driver27/api/serializers.py
driver27/api/viewsets.py
driver27/fixtures/driver27.json
driver27/locale/es/LC_MESSAGES/django.mo
driver27/locale/es/LC_MESSAGES/django.po
driver27/management/__init__.py
driver27/management/commands/__init__.py
driver27/management/commands/create_csv_for_result.py
driver27/management/commands/export_seats_for_csv.py
driver27/management/commands/import_seats_from_csv.py
driver27/management/commands/testing_multirecord.py
driver27/management/commands/update_results.py
driver27/migrations/0001_squashed.py
driver27/migrations/__init__.py
driver27/static/driver27/css/positions.css
driver27/static/driver27/css/style.css
driver27/static/driver27/js/filter_season_by_competition.js
driver27/static/driver27/js/list_filter_collapse.js
driver27/static/driver27/js/positions.js
driver27/static/driver27/js/select_default_circuit.js
driver27/templates/base.html
driver27/templates/driver27/_selector_competition.html
driver27/templates/driver27/_selector_menu.html
driver27/templates/driver27/_summary_profile.html
