Metadata-Version: 1.1
Name: django-driver27
Version: 0.24.2.5
Summary: Racing competition manager based on Django
Home-page: https://github.com/SRJ9/django-driver27.git
Author: Jose ER
Author-email: srj9es@gmail.com
License: MIT
Download-URL: https://github.com/SRJ9/django-driver27/archive/develop.zip
Keywords: Django,motorsport,formula one,formula 1,f1,manager
Platform: UNKNOWN
Classifier: Development Status :: 4 - Beta
Classifier: Framework :: Django
Classifier: Framework :: Django :: 1.10
Classifier: Framework :: Django :: 1.11
Classifier: Intended Audience :: Developers
Classifier: Intended Audience :: End Users/Desktop
Classifier: License :: OSI Approved :: MIT License
Classifier: Programming Language :: Python :: 2.7
Classifier: Programming Language :: Python :: 3.4
Classifier: Programming Language :: Python :: 3.5
Classifier: Programming Language :: Python :: 3.6
